LICENSE
MANIFEST.in
README.rst
manage.py
pavement.py
setup.py
bin/geosk-translations
bin/sk
bin/sk-updateip
bin/softInspector.sh
docs/Makefile
docs/conf.py
docs/index.rst
docs/index.rst~
docs/make.bat
docs/presentation.rst
docs/presentation.rst~
docs/pubblication.rst
docs/pubblication.rst~
docs/publication.rst
docs/publication.rst~
docs/_build/doctrees/environment.pickle
docs/_build/doctrees/index.doctree
docs/_build/doctrees/presentation.doctree
docs/_build/doctrees/pubblication.doctree
docs/_build/doctrees/publication.doctree
docs/_build/doctrees/glossary/edi.doctree
docs/_build/doctrees/tutorials/index.doctree
docs/_build/doctrees/tutorials/admin/advanced.doctree
docs/_build/doctrees/tutorials/admin/bing_maps_issue.doctree
docs/_build/doctrees/tutorials/admin/domain_name.doctree
docs/_build/doctrees/tutorials/admin/index.doctree
docs/_build/doctrees/tutorials/admin/quick.doctree
docs/_build/doctrees/tutorials/admin/scratch.doctree
docs/_build/doctrees/tutorials/admin/security_issue.doctree
docs/_build/doctrees/tutorials/admin/server.doctree
docs/_build/doctrees/tutorials/dataflowengine/index.doctree
docs/_build/doctrees/tutorials/dataflowengine/insertobservations.doctree
docs/_build/doctrees/tutorials/users/external_services.doctree
docs/_build/doctrees/tutorials/users/file_prj.doctree
docs/_build/doctrees/tutorials/users/index.doctree
docs/_build/doctrees/tutorials/users/metadati_sensori.doctree
docs/_build/doctrees/tutorials/users/plugin_qgis.doctree
docs/_build/doctrees/tutorials/users/servizi_jrc.doctree
docs/_build/doctrees/tutorials/users/sistemi_riferimento.doctree
docs/_build/doctrees/tutorials/users/utilizzo_wms.doctree
docs/_build/doctrees/tutorials/users/vincoli_dati.doctree
docs/_build/doctrees/tutorials/users/accounts_and_users/index.doctree
docs/_build/doctrees/tutorials/users/compilazione_metadati/index.doctree
docs/_build/doctrees/tutorials/users/compilazionemetadati/index.doctree
starterkit.egg-info/PKG-INFO
starterkit.egg-info/SOURCES.txt
starterkit.egg-info/dependency_links.txt
starterkit.egg-info/requires.txt
starterkit.egg-info/top_level.txt