Metadata-Version: 1.1
Name: starterkit
Version: 1.3.16
Summary: starterkit, based on GeoNode
Home-page: https://github.com/SP7-Ritmare/starterkit
Author: Starter Kit Development Team
Author-email: help.skritmare@irea.cnr.it
License: GPL3
Keywords: StarterKit GeoNode Django sensors SOS
Platform: UNKNOWN
Classifier: Development Status :: 4 - Beta
Classifier: License :: OSI Approved :: GNU General Public License v3 (GPLv3)
Classifier: Programming Language :: Python :: 2
